hub_driver_handler/__init__.py
hub_driver_handler/handler.py
hub_driver_handler/schema.py
hub_driver_handler/utils.py
hub_driver_handler-0.0.14.dist-info/METADATA
hub_driver_handler-0.0.14.dist-info/WHEEL
hub_driver_handler-0.0.14.dist-info/licenses/LICENSE
hub_driver_handler-0.0.14.dist-info/RECORD
