Metadata-Version: 2.4
Name: hub_driver_handler
Version: 0.0.14
Summary: Common driver handler for PPH
Author-email: Takahito Matsushima <takahito.matsushima@iot-ex.co.jp>
License-Expression: MIT
License-File: LICENSE
Classifier: Operating System :: OS Independent
Classifier: Programming Language :: Python :: 3
Requires-Python: >=3.9
